{
  "openapi": "3.0.1",
  "info": {
    "title": "ShoesShop API",
    "version": "v1"
  },
  "paths": {
    "/api/users/me/addresses": {
      "get": {
        "tags": [
          "Address"
        ],
        "responses": {
          "200": {
            "description": "OK"
          }
        }
      },
      "post": {
        "tags": [
          "Address"
        ],
        "requestBody": {
          "content": {
            "application/json": {
              "schema": {
                "$ref": "#/components/schemas/CreateAddressRequest"
              }
            },
            "text/json": {
              "schema": {
                "$ref": "#/components/schemas/CreateAddressRequest"
              }
            },
            "application/*+json": {
              "schema": {
                "$ref": "#/components/schemas/CreateAddressRequest"
              }
            }
          }
        },
        "responses": {
          "200": {
            "description": "OK"
          }
        }
      }
    },
    "/api/users/me/addresses/{addressId}": {
      "put": {
        "tags": [
          "Address"
        ],
        "parameters": [
          {
            "name": "addressId",
            "in": "path",
            "required": true,
            "schema": {
              "type": "integer",
              "format": "int32"
            }
          }
        ],
        "requestBody": {
          "content": {
            "application/json": {
              "schema": {
                "$ref": "#/components/schemas/UpdateAddressRequest"
              }
            },
            "text/json": {
              "schema": {
                "$ref": "#/components/schemas/UpdateAddressRequest"
              }
            },
            "application/*+json": {
              "schema": {
                "$ref": "#/components/schemas/UpdateAddressRequest"
              }
            }
          }
        },
        "responses": {
          "200": {
            "description": "OK"
          }
        }
      },
      "delete": {
        "tags": [
          "Address"
        ],
        "parameters": [
          {
            "name": "addressId",
            "in": "path",
            "required": true,
            "schema": {
              "type": "integer",
              "format": "int32"
            }
          }
        ],
        "responses": {
          "200": {
            "description": "OK"
          }
        }
      }
    },
    "/api/users/me/addresses/{addressId}/set-default": {
      "patch": {
        "tags": [
          "Address"
        ],
        "parameters": [
          {
            "name": "addressId",
            "in": "path",
            "required": true,
            "schema": {
              "type": "integer",
              "format": "int32"
            }
          }
        ],
        "responses": {
          "200": {
            "description": "OK"
          }
        }
      }
    },
    "/api/admin/users": {
      "get": {
        "tags": [
          "AdminUser"
        ],
        "parameters": [
          {
            "name": "search",
            "in": "query",
            "schema": {
              "type": "string"
            }
          },
          {
            "name": "page",
            "in": "query",
            "schema": {
              "type": "integer",
              "format": "int32",
              "default": 1
            }
          },
          {
            "name": "pageSize",
            "in": "query",
            "schema": {
              "type": "integer",
              "format": "int32",
              "default": 10
            }
          }
        ],
        "responses": {
          "200": {
            "description": "OK"
          }
        }
      }
    },
    "/api/admin/users/{userId}/lock": {
      "patch": {
        "tags": [
          "AdminUser"
        ],
        "parameters": [
          {
            "name": "userId",
            "in": "path",
            "required": true,
            "schema": {
              "type": "integer",
              "format": "int32"
            }
          }
        ],
        "responses": {
          "200": {
            "description": "OK"
          }
        }
      }
    },
    "/api/admin/users/{userId}/unlock": {
      "patch": {
        "tags": [
          "AdminUser"
        ],
        "parameters": [
          {
            "name": "userId",
            "in": "path",
            "required": true,
            "schema": {
              "type": "integer",
              "format": "int32"
            }
          }
        ],
        "responses": {
          "200": {
            "description": "OK"
          }
        }
      }
    },
    "/api/admin/users/{userId}/role": {
      "patch": {
        "tags": [
          "AdminUser"
        ],
        "parameters": [
          {
            "name": "userId",
            "in": "path",
            "required": true,
            "schema": {
              "type": "integer",
              "format": "int32"
            }
          }
        ],
        "requestBody": {
          "content": {
            "application/json": {
              "schema": {
                "$ref": "#/components/schemas/AdminUpdateRoleRequest"
              }
            },
            "text/json": {
              "schema": {
                "$ref": "#/components/schemas/AdminUpdateRoleRequest"
              }
            },
            "application/*+json": {
              "schema": {
                "$ref": "#/components/schemas/AdminUpdateRoleRequest"
              }
            }
          }
        },
        "responses": {
          "200": {
            "description": "OK"
          }
        }
      }
    },
    "/api/auth/register": {
      "post": {
        "tags": [
          "Auth"
        ],
        "requestBody": {
          "content": {
            "application/json": {
              "schema": {
                "$ref": "#/components/schemas/RegisterRequest"
              }
            },
            "text/json": {
              "schema": {
                "$ref": "#/components/schemas/RegisterRequest"
              }
            },
            "application/*+json": {
              "schema": {
                "$ref": "#/components/schemas/RegisterRequest"
              }
            }
          }
        },
        "responses": {
          "200": {
            "description": "OK"
          }
        }
      }
    },
    "/api/auth/login": {
      "post": {
        "tags": [
          "Auth"
        ],
        "requestBody": {
          "content": {
            "application/json": {
              "schema": {
                "$ref": "#/components/schemas/LoginRequest"
              }
            },
            "text/json": {
              "schema": {
                "$ref": "#/components/schemas/LoginRequest"
              }
            },
            "application/*+json": {
              "schema": {
                "$ref": "#/components/schemas/LoginRequest"
              }
            }
          }
        },
        "responses": {
          "200": {
            "description": "OK"
          }
        }
      }
    },
    "/api/auth/logout": {
      "post": {
        "tags": [
          "Auth"
        ],
        "responses": {
          "200": {
            "description": "OK"
          }
        }
      }
    },
    "/api/auth/me": {
      "get": {
        "tags": [
          "Auth"
        ],
        "responses": {
          "200": {
            "description": "OK"
          }
        }
      }
    },
    "/api/users/me/profile": {
      "get": {
        "tags": [
          "UserProfile"
        ],
        "responses": {
          "200": {
            "description": "OK"
          }
        }
      },
      "put": {
        "tags": [
          "UserProfile"
        ],
        "requestBody": {
          "content": {
            "application/json": {
              "schema": {
                "$ref": "#/components/schemas/UpdateProfileRequest"
              }
            },
            "text/json": {
              "schema": {
                "$ref": "#/components/schemas/UpdateProfileRequest"
              }
            },
            "application/*+json": {
              "schema": {
                "$ref": "#/components/schemas/UpdateProfileRequest"
              }
            }
          }
        },
        "responses": {
          "200": {
            "description": "OK"
          }
        }
      }
    },
    "/WeatherForecast": {
      "get": {
        "tags": [
          "WeatherForecast"
        ],
        "operationId": "GetWeatherForecast",
        "responses": {
          "200": {
            "description": "OK",
            "content": {
              "text/plain": {
                "schema": {
                  "type": "array",
                  "items": {
                    "$ref": "#/components/schemas/WeatherForecast"
                  }
                }
              },
              "application/json": {
                "schema": {
                  "type": "array",
                  "items": {
                    "$ref": "#/components/schemas/WeatherForecast"
                  }
                }
              },
              "text/json": {
                "schema": {
                  "type": "array",
                  "items": {
                    "$ref": "#/components/schemas/WeatherForecast"
                  }
                }
              }
            }
          }
        }
      }
    }
  },
  "components": {
    "schemas": {
      "AdminUpdateRoleRequest": {
        "required": [
          "roleName"
        ],
        "type": "object",
        "properties": {
          "roleName": {
            "minLength": 1,
            "type": "string"
          }
        },
        "additionalProperties": false
      },
      "CreateAddressRequest": {
        "required": [
          "district",
          "phone",
          "province",
          "recipientName",
          "streetAddress",
          "ward"
        ],
        "type": "object",
        "properties": {
          "recipientName": {
            "maxLength": 100,
            "minLength": 1,
            "type": "string"
          },
          "phone": {
            "maxLength": 20,
            "minLength": 1,
            "type": "string"
          },
          "province": {
            "maxLength": 100,
            "minLength": 1,
            "type": "string"
          },
          "district": {
            "maxLength": 100,
            "minLength": 1,
            "type": "string"
          },
          "ward": {
            "maxLength": 100,
            "minLength": 1,
            "type": "string"
          },
          "streetAddress": {
            "maxLength": 255,
            "minLength": 1,
            "type": "string"
          },
          "isDefault": {
            "type": "boolean"
          }
        },
        "additionalProperties": false
      },
      "LoginRequest": {
        "required": [
          "email",
          "password"
        ],
        "type": "object",
        "properties": {
          "email": {
            "minLength": 1,
            "type": "string",
            "format": "email"
          },
          "password": {
            "minLength": 1,
            "type": "string"
          }
        },
        "additionalProperties": false
      },
      "RegisterRequest": {
        "required": [
          "email",
          "fullName",
          "password"
        ],
        "type": "object",
        "properties": {
          "email": {
            "minLength": 1,
            "type": "string",
            "format": "email"
          },
          "password": {
            "minLength": 6,
            "type": "string"
          },
          "fullName": {
            "maxLength": 100,
            "minLength": 1,
            "type": "string"
          },
          "phone": {
            "maxLength": 20,
            "type": "string",
            "nullable": true
          }
        },
        "additionalProperties": false
      },
      "UpdateAddressRequest": {
        "required": [
          "district",
          "phone",
          "province",
          "recipientName",
          "streetAddress",
          "ward"
        ],
        "type": "object",
        "properties": {
          "recipientName": {
            "maxLength": 100,
            "minLength": 1,
            "type": "string"
          },
          "phone": {
            "maxLength": 20,
            "minLength": 1,
            "type": "string"
          },
          "province": {
            "maxLength": 100,
            "minLength": 1,
            "type": "string"
          },
          "district": {
            "maxLength": 100,
            "minLength": 1,
            "type": "string"
          },
          "ward": {
            "maxLength": 100,
            "minLength": 1,
            "type": "string"
          },
          "streetAddress": {
            "maxLength": 255,
            "minLength": 1,
            "type": "string"
          },
          "isDefault": {
            "type": "boolean"
          }
        },
        "additionalProperties": false
      },
      "UpdateProfileRequest": {
        "required": [
          "fullName"
        ],
        "type": "object",
        "properties": {
          "fullName": {
            "maxLength": 100,
            "minLength": 1,
            "type": "string"
          },
          "phone": {
            "maxLength": 20,
            "type": "string",
            "nullable": true
          },
          "dateOfBirth": {
            "type": "string",
            "format": "date",
            "nullable": true
          },
          "gender": {
            "maxLength": 10,
            "type": "string",
            "nullable": true
          },
          "avatarUrl": {
            "maxLength": 500,
            "type": "string",
            "nullable": true
          }
        },
        "additionalProperties": false
      },
      "WeatherForecast": {
        "type": "object",
        "properties": {
          "date": {
            "type": "string",
            "format": "date"
          },
          "temperatureC": {
            "type": "integer",
            "format": "int32"
          },
          "temperatureF": {
            "type": "integer",
            "format": "int32",
            "readOnly": true
          },
          "summary": {
            "type": "string",
            "nullable": true
          }
        },
        "additionalProperties": false
      }
    },
    "securitySchemes": {
      "Bearer": {
        "type": "http",
        "description": "Nhap JWT token. Vi du: Bearer eyJhbGci...",
        "scheme": "bearer",
        "bearerFormat": "JWT"
      }
    }
  },
  "security": [
    {
      "Bearer": [ ]
    }
  ]
}